iamge_processing/__init__.py
iamge_processing/processing/__init__.py
iamge_processing/processing/combination.py
iamge_processing/processing/transformation.py
iamge_processing/utils/__init__.py
iamge_processing/utils/io.py
iamge_processing/utils/plot.py
packege_name-0.0.1.dist-info/METADATA
packege_name-0.0.1.dist-info/WHEEL
packege_name-0.0.1.dist-info/top_level.txt
packege_name-0.0.1.dist-info/RECORD
