Metadata-Version: 2.1
Name: packege-name
Version: 0.0.1
Summary: My short description
Home-page: https://github.com/caio-alberto/image_processing.git
Author: caio777
Author-email: caio777alberto7@gmail.com
Requires-Python: >=3.8
Requires-Dist: matplotlib
Requires-Dist: numpy
Requires-Dist: scikit-image (>=0.16.1)
